pydbgen/Domains.txt
pydbgen/US_Cities.txt
pydbgen/pydbgen.py
pydbgen-1.0.5.dist-info/DESCRIPTION.rst
pydbgen-1.0.5.dist-info/METADATA
pydbgen-1.0.5.dist-info/RECORD
pydbgen-1.0.5.dist-info/WHEEL
pydbgen-1.0.5.dist-info/metadata.json
pydbgen-1.0.5.dist-info/top_level.txt
