Metadata-Version: 2.0
Name: pydbgen
Version: 1.0.5
Summary: Random database/dataframe generator
Home-page: https://github.com/tirthajyoti/pydbgen
Author: Tirthajyoti Sarkar
Author-email: tirthajyoti@gmail.com
License: MIT
Keywords: database random dataframe sqlite
Platform: UNKNOWN
Classifier: Development Status :: 3 - Alpha
Classifier: Environment :: Console
Classifier: Intended Audience :: Developers
Classifier: License :: OSI Approved :: MIT License
Classifier: Operating System :: OS Independent
Classifier: Programming Language :: Python :: 3.6
Classifier: Topic :: Database
Classifier: Topic :: Utilities
Requires-Dist: Faker
Requires-Dist: Pandas
Requires-Dist: six
